azure/ai/textanalytics/authoring/__init__.py
azure/ai/textanalytics/authoring/_client.py
azure/ai/textanalytics/authoring/_configuration.py
azure/ai/textanalytics/authoring/_patch.py
azure/ai/textanalytics/authoring/_validation.py
azure/ai/textanalytics/authoring/_version.py
azure/ai/textanalytics/authoring/py.typed
azure/ai/textanalytics/authoring/_utils/__init__.py
azure/ai/textanalytics/authoring/_utils/model_base.py
azure/ai/textanalytics/authoring/_utils/serialization.py
azure/ai/textanalytics/authoring/_utils/utils.py
azure/ai/textanalytics/authoring/aio/__init__.py
azure/ai/textanalytics/authoring/aio/_client.py
azure/ai/textanalytics/authoring/aio/_configuration.py
azure/ai/textanalytics/authoring/aio/_patch.py
azure/ai/textanalytics/authoring/aio/operations/__init__.py
azure/ai/textanalytics/authoring/aio/operations/_operations.py
azure/ai/textanalytics/authoring/aio/operations/_patch.py
azure/ai/textanalytics/authoring/models/__init__.py
azure/ai/textanalytics/authoring/models/_enums.py
azure/ai/textanalytics/authoring/models/_models.py
azure/ai/textanalytics/authoring/models/_patch.py
azure/ai/textanalytics/authoring/operations/__init__.py
azure/ai/textanalytics/authoring/operations/_operations.py
azure/ai/textanalytics/authoring/operations/_patch.py
azure_ai_textanalytics_authoring-1.0.0b1.dist-info/licenses/LICENSE
azure_ai_textanalytics_authoring-1.0.0b1.dist-info/METADATA
azure_ai_textanalytics_authoring-1.0.0b1.dist-info/WHEEL
azure_ai_textanalytics_authoring-1.0.0b1.dist-info/top_level.txt
azure_ai_textanalytics_authoring-1.0.0b1.dist-info/RECORD
