Metadata-Version: 2.4
Name: azure-ai-textanalytics-authoring
Version: 1.0.0b1
Summary: Microsoft Corporation Azure Ai Textanalytics Authoring Client Library for Python
Author-email: Microsoft Corporation <azpysdkhelp@microsoft.com>
License-Expression: MIT
Project-URL: repository, https://github.com/Azure/azure-sdk-for-python
Keywords: azure,azure sdk
Classifier: Development Status :: 4 - Beta
Classifier: Programming Language :: Python
Classifier: Programming Language :: Python :: 3 :: Only
Classifier: Programming Language :: Python :: 3
Classifier: Programming Language :: Python :: 3.9
Classifier: Programming Language :: Python :: 3.10
Classifier: Programming Language :: Python :: 3.11
Classifier: Programming Language :: Python :: 3.12
Classifier: Programming Language :: Python :: 3.13
Requires-Python: >=3.9
License-File: LICENSE
Requires-Dist: isodate>=0.6.1
Requires-Dist: azure-core>=1.35.0
Requires-Dist: typing-extensions>=4.6.0
Requires-Dist: azure-ai-textanalytics>=6.0.0b1
Dynamic: license-file
